{
  "filename": "Screenshot_20251021-010516 (1).webp",
  "tags": [
    "screenshot",
    "streaming",
    "movies",
    "website",
    "entertainment",
    "advertisement",
    "mobile",
    "cinema",
    "film",
    "media"
  ],
  "raw_text": "8. CINEB.RS\nStream movies still in theaters, no login, totally free. Works on mobile. Works too well.\nCineb.net\nEnter keywords...\nLogin / Register\nEver wanted to watch free movies online? Then look no further. Watch movies of various categories only here. Stream HD quality movies on your TV, laptop or mobile. Here you can watch the movies of your choice without any registration or signups - most hassle free option. Stop visiting terrible sites that promise movies in HD and 4K quality and serve you crap, and waste your time and energy. You can easily search the movies of your choice here: from blockbusters to rare critically acclaimed gems, we have them all. We promise regular uploads. So, your favorite movie is just a click away! Think no more, start streaming\nTwitter Facebook WhatsApp Pinterest Telegram Email More 345\nTRY OUR Android Apk now DOWNLOAD\nFeatured\nSNOWPIERCER\nIRRESISTIBLE\nFanny Lye Deliver'd\nEUROVISION\nSTARGIRL\nDARK\nLikes",
  "structured_data": {
    "title": "8. CINEB.RS",
    "description": "Stream movies still in theaters, no login, totally free. Works on mobile. Works too well.",
    "website_preview": {
      "domain": "Cineb.net",
      "features": [
        "No registration required",
        "HD quality",
        "Android APK available",
        "Mobile friendly"
      ],
      "visible_titles": [
        "Snowpiercer",
        "Irresistible",
        "Fanny Lye Deliver'd",
        "Eurovision Song Contest: The Story of Fire Saga",
        "Stargirl",
        "Dark",
        "Dune",
        "Madame Web",
        "Argylle"
      ]
    }
  },
  "profile_mentions": [],
  "additional_metadata": {
    "urls": [
      "CINEB.RS",
      "Cineb.net"
    ],
    "social_share_options": [
      "Twitter",
      "Facebook",
      "WhatsApp",
      "Pinterest",
      "Telegram",
      "Email"
    ],
    "app_platforms": [
      "Android"
    ]
  }
}